TOPSIS_Ritikkumar_101983054/__init__.py
TOPSIS_Ritikkumar_101983054-1.2.0.dist-info/LICENSE
TOPSIS_Ritikkumar_101983054-1.2.0.dist-info/METADATA
TOPSIS_Ritikkumar_101983054-1.2.0.dist-info/WHEEL
TOPSIS_Ritikkumar_101983054-1.2.0.dist-info/top_level.txt
TOPSIS_Ritikkumar_101983054-1.2.0.dist-info/RECORD
