Metadata-Version: 2.1
Name: TOPSIS-Ritikkumar-101983054
Version: 1.2.0
Summary: Technique for Oder Preference by Similarity to Ideal Solution.
Home-page: https://github.com/ritik-sys/TOPSIS_package
Author: Ritik Kumar
Author-email: rkumar2_be18@thapar.edu
License: UNKNOWN
Platform: UNKNOWN
Classifier: Programming Language :: Python :: 3
Classifier: License :: OSI Approved :: MIT License
Classifier: Operating System :: OS Independent
Requires-Python: >=3.6
